[
  {
    "skill_id": "ana1-etude-02",
    "difficulty": 2,
    "validation": "manual",
    "payload": {
      "skill_id": "ana1-etude-02",
      "format": "qcm",
      "difficulty": 2,
      "statement_latex": "Soit $f$ la fonction d\\'efinie par $f(x) = \\dfrac{x^2 - 4}{x - 2}$. Quel est le tableau de variations complet de $f$ ?",
      "hints": [
        "La fonction $f$ est d\\'efinie sur $\\mathbb{R} \\setminus \\{2\\}$.",
        "La d\\'eriv\\'ee de $f$ est $f'(x) = \\dfrac{(x-2)(2x) - (x^2-4)(1)}{(x-2)^2} = \\dfrac{x^2 - 4x - 4}{(x-2)^2}$"
      ],
      "solution_latex": "Le tableau de variations complet de $f$ est : $\\begin{array}{|c|c|c|c|c|} \\hline x & -\\infty & -2 & 2 & +\\infty \\\\ \\hline f(x) & -\\infty & 0 & \\text{nd} & +\\infty \\\\ \\hline f'(x) & + & 0 & - & + \\\\ \\hline \\text{Variations de } f & \\nearrow & \\nearrow & \\searrow & \\nearrow \\\\ \\hline \\end{array}$",
      "choices": [
        {
          "latex": "$\\begin{array}{|c|c|c|c|c|} \\hline x & -\\infty & -2 & 2 & +\\infty \\\\ \\hline f(x) & -\\infty & 0 & \\text{nd} & +\\infty \\\\ \\hline f'(x) & + & 0 & - & + \\\\ \\hline \\text{Variations de } f & \\nearrow & \\nearrow & \\searrow & \\nearrow \\\\ \\hline \\end{array}$",
          "sympy": "x**2 - 4",
          "correct": true,
          "error_type": ""
        },
        {
          "latex": "$\\begin{array}{|c|c|c|c|c|} \\hline x & -\\infty & -2 & 2 & +\\infty \\\\ \\hline f(x) & -\\infty & 0 & \\text{nd} & +\\infty \\\\ \\hline f'(x) & - & 0 & + & - \\\\ \\hline \\text{Variations de } f & \\searrow & \\searrow & \\nearrow & \\searrow \\\\ \\hline \\end{array}$",
          "sympy": "-x**2 + 4",
          "correct": false,
          "error_type": "sign_error_in_derivative"
        },
        {
          "latex": "$\\begin{array}{|c|c|c|c|c|} \\hline x & -\\infty & -2 & 2 & +\\infty \\\\ \\hline f(x) & +\\infty & 0 & \\text{nd} & -\\infty \\\\ \\hline f'(x) & + & 0 & - & + \\\\ \\hline \\text{Variations de } f & \\searrow & \\searrow & \\nearrow & \\searrow \\\\ \\hline \\end{array}$",
          "sympy": "4 - x**2",
          "correct": false,
          "error_type": "inversion_asymptote"
        },
        {
          "latex": "$\\begin{array}{|c|c|c|c|c|} \\hline x & -\\infty & -2 & 2 & +\\infty \\\\ \\hline f(x) & -\\infty & 0 & \\text{nd} & +\\infty \\\\ \\hline f'(x) & + & 0 & - & + \\\\ \\hline \\text{Variations de } f & \\nearrow & \\searrow & \\nearrow & \\searrow \\\\ \\hline \\end{array}$",
          "sympy": "x**2 + 4",
          "correct": false,
          "error_type": "wrong_trend"
        }
      ],
      "check": {
        "kind": "manual"
      }
    }
  },
  {
    "skill_id": "ana1-etude-02",
    "difficulty": 3,
    "validation": "manual",
    "payload": {
      "skill_id": "ana1-etude-02",
      "format": "qcm",
      "difficulty": 3,
      "statement_latex": "Soit $f$ la fonction d\\'efinie par $f(x) = x^3 - 6x^2 + 9x + 2$. Quel est le tableau de variations complet de $f$ ?",
      "hints": [
        "La fonction $f$ est d\\'efinie sur $\\mathbb{R}$.",
        "La d\\'eriv\\'ee de $f$ est $f'(x) = 3x^2 - 12x + 9$."
      ],
      "solution_latex": "Le tableau de variations complet de $f$ est : $\\begin{array}{|c|c|c|c|c|} \\hline x & -\\infty & 1 & 3 & +\\infty \\\\ \\hline f(x) & -\\infty & 6 & -4 & +\\infty \\\\ \\hline f'(x) & + & 0 & 0 & + \\\\ \\hline \\text{Variations de } f & \\nearrow & \\searrow & \\nearrow & \\nearrow \\\\ \\hline \\end{array}$",
      "choices": [
        {
          "latex": "$\\begin{array}{|c|c|c|c|c|} \\hline x & -\\infty & 1 & 3 & +\\infty \\\\ \\hline f(x) & -\\infty & 6 & -4 & +\\infty \\\\ \\hline f'(x) & + & 0 & 0 & + \\\\ \\hline \\text{Variations de } f & \\nearrow & \\searrow & \\nearrow & \\nearrow \\\\ \\hline \\end{array}$",
          "sympy": "x**3 - 6*x**2 + 9*x + 2",
          "correct": true,
          "error_type": ""
        },
        {
          "latex": "$\\begin{array}{|c|c|c|c|c|} \\hline x & -\\infty & 1 & 3 & +\\infty \\\\ \\hline f(x) & +\\infty & 6 & -4 & -\\infty \\\\ \\hline f'(x) & - & 0 & 0 & - \\\\ \\hline \\text{Variations de } f & \\searrow & \\nearrow & \\searrow & \\searrow \\\\ \\hline \\end{array}$",
          "sympy": "-x**3 + 6*x**2 - 9*x - 2",
          "correct": false,
          "error_type": "derivative_sign_error"
        },
        {
          "latex": "$\\begin{array}{|c|c|c|c|c|} \\hline x & -\\infty & 1 & 3 & +\\infty \\\\ \\hline f(x) & -\\infty & 6 & -4 & +\\infty \\\\ \\hline f'(x) & + & 0 & 0 & + \\\\ \\hline \\text{Variations de } f & \\searrow & \\nearrow & \\searrow & \\nearrow \\\\ \\hline \\end{array}$",
          "sympy": "x**3 + 6*x**2 + 9*x + 2",
          "correct": false,
          "error_type": "wrong_extremum_position"
        },
        {
          "latex": "$\\begin{array}{|c|c|c|c|c|} \\hline x & -\\infty & 1 & 3 & +\\infty \\\\ \\hline f(x) & -\\infty & 6 & -4 & +\\infty \\\\ \\hline f'(x) & - & 0 & 0 & - \\\\ \\hline \\text{Variations de } f & \\nearrow & \\searrow & \\nearrow & \\searrow \\\\ \\hline \\end{array}$",
          "sympy": "-x**3 - 6*x**2 - 9*x - 2",
          "correct": false,
          "error_type": "inconsistent_trends"
        }
      ],
      "check": {
        "kind": "manual"
      }
    }
  },
  {
    "skill_id": "ana1-etude-02",
    "difficulty": 2,
    "validation": "manual",
    "payload": {
      "skill_id": "ana1-etude-02",
      "format": "qcm",
      "difficulty": 2,
      "statement_latex": "Soit $f$ la fonction d\\'efinie par $f(x) = \\dfrac{1}{x}$. Quel est le tableau de variations complet de $f$ ?",
      "hints": [
        "La fonction $f$ est d\\'efinie sur $\\mathbb{R} \\setminus \\{0\\}$.",
        "La d\\'eriv\\'ee de $f$ est $f'(x) = -\\dfrac{1}{x^2}$."
      ],
      "solution_latex": "Le tableau de variations complet de $f$ est : $\\begin{array}{|c|c|c|c|c|} \\hline x & -\\infty & 0 & +\\infty \\\\ \\hline f(x) & 0 & \\text{nd} & 0 \\\\ \\hline f'(x) & + & - & - \\\\ \\hline \\text{Variations de } f & \\searrow & \\nearrow & \\searrow \\\\ \\hline \\end{array}$",
      "choices": [
        {
          "latex": "$\\begin{array}{|c|c|c|c|c|} \\hline x & -\\infty & 0 & +\\infty \\\\ \\hline f(x) & 0 & \\text{nd} & 0 \\\\ \\hline f'(x) & + & - & - \\\\ \\hline \\text{Variations de } f & \\searrow & \\nearrow & \\searrow \\\\ \\hline \\end{array}$",
          "sympy": "1/x",
          "correct": true,
          "error_type": ""
        },
        {
          "latex": "$\\begin{array}{|c|c|c|c|c|} \\hline x & -\\infty & 0 & +\\infty \\\\ \\hline f(x) & 0 & \\text{nd} & 0 \\\\ \\hline f'(x) & - & + & + \\\\ \\hline \\text{Variations de } f & \\nearrow & \\searrow & \\nearrow \\\\ \\hline \\end{array}$",
          "sympy": "-1/x",
          "correct": false,
          "error_type": "derivative_sign_mistake"
        },
        {
          "latex": "$\\begin{array}{|c|c|c|c|c|} \\hline x & -\\infty & 0 & +\\infty \\\\ \\hline f(x) & 0 & \\text{nd} & 0 \\\\ \\hline f'(x) & + & - & - \\\\ \\hline \\text{Variations de } f & \\nearrow & \\searrow & \\nearrow \\\\ \\hline \\end{array}$",
          "sympy": "x",
          "correct": false,
          "error_type": "function_confusion"
        },
        {
          "latex": "$\\begin{array}{|c|c|c|c|c|} \\hline x & -\\infty & 0 & +\\infty \\\\ \\hline f(x) & 0 & \\text{nd} & 0 \\\\ \\hline f'(x) & - & + & - \\\\ \\hline \\text{Variations de } f & \\searrow & \\nearrow & \\searrow \\\\ \\hline \\end{array}$",
          "sympy": "-x",
          "correct": false,
          "error_type": "asymptote_missing"
        }
      ],
      "check": {
        "kind": "manual"
      }
    }
  },
  {
    "skill_id": "ana1-etude-02",
    "difficulty": 2,
    "validation": "manual",
    "payload": {
      "skill_id": "ana1-etude-02",
      "format": "qcm",
      "difficulty": 2,
      "statement_latex": "Soit $f$ la fonction d'efinie par $f(x) = x^2 - 3x + 2$. Quel est le tableau de variations complet de $f$ ?",
      "hints": [
        "La fonction $f$ est une fonction quadratique.",
        "Pour construire le tableau de variations, il faut calculer la d'eriv'ee de $f$, trouver les limites aux bornes et d'eterminer le signe de $f'$."
      ],
      "solution_latex": "Le tableau de variations complet de $f$ est :\\begin{array}{|c|c|c|c|c|}\\hline x & -\\infty & 1 & 2 & +\\infty \\\\ \\hline f'(x) & & 0 & & \\\\ \\hline f(x) & +\\infty & 0 & -1 & +\\infty \\\\ \\hline \\end{array}",
      "choices": [
        {
          "latex": "\\begin{array}{|c|c|c|c|c|} \\hline x & -\\infty & 1 & 2 & +\\infty \\\\ \\hline f'(x) & & 0 & & \\\\ \\hline f(x) & +\\infty & 0 & -1 & +\\infty \\\\ \\hline \\end{array}",
          "sympy": "x**2 - 3*x + 2",
          "correct": true,
          "error_type": null
        },
        {
          "latex": "\\begin{array}{|c|c|c|c|c|} \\hline x & -\\infty & 1 & 2 & +\\infty \\\\ \\hline f'(x) & & 0 & & \\\\ \\hline f(x) & -\\infty & 0 & -1 & +\\infty \\\\ \\hline \\end{array}",
          "sympy": "x**2 - 3*x - 2",
          "correct": false,
          "error_type": "signe_de_f_incorrect"
        },
        {
          "latex": "\\begin{array}{|c|c|c|c|c|} \\hline x & -\\infty & 1 & 2 & +\\infty \\\\ \\hline f'(x) & & 0 & & \\\\ \\hline f(x) & +\\infty & 0 & 1 & +\\infty \\\\ \\hline \\end{array}",
          "sympy": "x**2 - 3*x + 1",
          "correct": false,
          "error_type": "valeur_de_f_incorrecte"
        },
        {
          "latex": "\\begin{array}{|c|c|c|c|c|} \\hline x & -\\infty & 2 & 1 & +\\infty \\\\ \\hline f'(x) & & 0 & & \\\\ \\hline f(x) & +\\infty & 0 & -1 & +\\infty \\\\ \\hline \\end{array}",
          "sympy": "x**2 - 3*x - 2",
          "correct": false,
          "error_type": "inversion_des_zero_de_f"
        }
      ],
      "check": {
        "kind": "manual"
      }
    }
  },
  {
    "skill_id": "ana1-etude-02",
    "difficulty": 3,
    "validation": "manual",
    "payload": {
      "skill_id": "ana1-etude-02",
      "format": "qcm",
      "difficulty": 3,
      "statement_latex": "Soit $f$ la fonction d'efinie par $f(x) = \\dfrac{x^2 - 1}{x + 1}$. Quel est le tableau de variations complet de $f$ ?",
      "hints": [
        "La fonction $f$ est une fonction rationnelle.",
        "Pour construire le tableau de variations, il faut calculer la d'eriv'ee de $f$, trouver les limites aux bornes et d'eterminer le signe de $f'$."
      ],
      "solution_latex": "Le tableau de variations complet de $f$ est :\\begin{array}{|c|c|c|c|c|} \\hline x & -\\infty & -1 & 1 & +\\infty \\\\ \\hline f'(x) & & & 0 & \\\\ \\hline f(x) & -2 & - & 0 & 1 \\\\ \\hline \\end{array}",
      "choices": [
        {
          "latex": "\\begin{array}{|c|c|c|c|c|} \\hline x & -\\infty & -1 & 1 & +\\infty \\\\ \\hline f'(x) & & & 0 & \\\\ \\hline f(x) & -2 & - & 0 & 1 \\\\ \\hline \\end{array}",
          "sympy": "(x**2 - 1)/(x + 1)",
          "correct": true,
          "error_type": null
        },
        {
          "latex": "\\begin{array}{|c|c|c|c|c|} \\hline x & -\\infty & -1 & 1 & +\\infty \\\\ \\hline f'(x) & & & 0 & \\\\ \\hline f(x) & -2 & - & 0 & -1 \\\\ \\hline \\end{array}",
          "sympy": "(x**2 - 1)/(x - 1)",
          "correct": false,
          "error_type": "valeur_de_f_incorrecte"
        },
        {
          "latex": "\\begin{array}{|c|c|c|c|c|} \\hline x & -\\infty & 1 & -1 & +\\infty \\\\ \\hline f'(x) & & 0 & & \\\\ \\hline f(x) & -2 & 0 & - & 1 \\\\ \\hline \\end{array}",
          "sympy": "(x**2 - 1)/(x - 1)",
          "correct": false,
          "error_type": "inversion_des_zero_de_f"
        },
        {
          "latex": "\\begin{array}{|c|c|c|c|c|} \\hline x & -\\infty & -1 & 1 & +\\infty \\\\ \\hline f'(x) & & & & \\\\ \\hline f(x) & -2 & - & 0 & 1 \\\\ \\hline \\end{array}",
          "sympy": "(x**2 - 1)/(x + 1)",
          "correct": false,
          "error_type": "derivative_not_calculated"
        }
      ],
      "check": {
        "kind": "manual"
      }
    }
  },
  {
    "skill_id": "ana1-etude-02",
    "difficulty": 2,
    "validation": "manual",
    "payload": {
      "skill_id": "ana1-etude-02",
      "format": "qcm",
      "difficulty": 2,
      "statement_latex": "Soit $f$ la fonction d'efinie par $f(x) = x^3 - 3x^2$. Quel est le tableau de variations complet de $f$ ?",
      "hints": [
        "La fonction $f$ est une fonction cubique.",
        "Pour construire le tableau de variations, il faut calculer la d'eriv'ee de $f$, trouver les limites aux bornes et d'eterminer le signe de $f'$."
      ],
      "solution_latex": "Le tableau de variations complet de $f$ est :\\begin{array}{|c|c|c|c|c|} \\hline x & -\\infty & 0 & 1 & 3 & +\\infty \\\\ \\hline f'(x) & & 0 & -3 & 0 & \\\\ \\hline f(x) & -\\infty & 0 & -2 & 0 & +\\infty \\\\ \\hline \\end{array}",
      "choices": [
        {
          "latex": "\\begin{array}{|c|c|c|c|c|} \\hline x & -\\infty & 0 & 1 & 3 & +\\infty \\\\ \\hline f'(x) & & 0 & -3 & 0 & \\\\ \\hline f(x) & -\\infty & 0 & -2 & 0 & +\\infty \\\\ \\hline \\end{array}",
          "sympy": "x**3 - 3*x**2",
          "correct": true,
          "error_type": null
        },
        {
          "latex": "\\begin{array}{|c|c|c|c|c|} \\hline x & -\\infty & 0 & 1 & 3 & +\\infty \\\\ \\hline f'(x) & & 0 & 3 & 0 & \\\\ \\hline f(x) & -\\infty & 0 & -2 & 0 & +\\infty \\\\ \\hline \\end{array}",
          "sympy": "x**3 + 3*x**2",
          "correct": false,
          "error_type": "signe_de_f_incorrect"
        },
        {
          "latex": "\\begin{array}{|c|c|c|c|c|} \\hline x & -\\infty & 0 & 1 & 3 & +\\infty \\\\ \\hline f'(x) & & 0 & -3 & 0 & \\\\ \\hline f(x) & +\\infty & 0 & -2 & 0 & +\\infty \\\\ \\hline \\end{array}",
          "sympy": "-x**3 - 3*x**2",
          "correct": false,
          "error_type": "valeur_de_f_incorrecte"
        },
        {
          "latex": "\\begin{array}{|c|c|c|c|c|} \\hline x & -\\infty & 1 & 0 & 3 & +\\infty \\\\ \\hline f'(x) & & -3 & 0 & 0 & \\\\ \\hline f(x) & -\\infty & -2 & 0 & 0 & +\\infty \\\\ \\hline \\end{array}",
          "sympy": "-x**3 + 3*x**2",
          "correct": false,
          "error_type": "inversion_des_zero_de_f"
        }
      ],
      "check": {
        "kind": "manual"
      }
    }
  },
  {
    "skill_id": "ana1-etude-02",
    "difficulty": 2,
    "validation": "manual",
    "payload": {
      "skill_id": "ana1-etude-02",
      "format": "qcm",
      "difficulty": 2,
      "statement_latex": "Soit $f$ la fonction d'efinie par $f(x) = x^2 - 2x - 3$. Quel est le tableau de variations complet de $f$ ?",
      "hints": [
        "Étudiez d'abord la dérivée de la fonction pour connaître les intervalles de variation.",
        "Construisez ensuite le tableau de variations en considérant les limites aux bornes et les valeurs remarquables."
      ],
      "solution_latex": "Le tableau de variations complet de $f$ est donné par : \\begin{tabular}{|c|c|c|c|c|}hline Intervalles & $(-\\infty,-1)$ & $(-1,3)$ & $(3,+\\infty)$ \\\\ \\hline Signe de $f'(x)$ & $+$ & $-$ & $+$ \\\\ \\hline Variations de $f$ & $\\nearrow$ & $\\searrow$ & $\\nearrow$ \\\\ \\hline Limites aux bornes & $\\lim\\limits_{x\\to -\\infty} f(x) = +\\infty$ & & $\\lim\\limits_{x\\to +\\infty} f(x) = +\\infty$ \\\\ \\hline Valeurs remarquables & $f(-1) = 0$ & $f(3) = 0$ & \\\\ \\hline end{tabular}",
      "choices": [
        {
          "latex": "Le tableau de variations complet de $f$ est donné par : \\begin{tabular}{|c|c|c|c|c|}hline Intervalles & $(-\\infty,-1)$ & $(-1,3)$ & $(3,+\\infty)$ \\\\ \\hline Signe de $f'(x)$ & $+$ & $-$ & $+$ \\\\ \\hline Variations de $f$ & $\\nearrow$ & $\\searrow$ & $\\nearrow$ \\\\ \\hline Limites aux bornes & $\\lim\\limits_{x\\to -\\infty} f(x) = +\\infty$ & & $\\lim\\limits_{x\\to +\\infty} f(x) = +\\infty$ \\\\ \\hline Valeurs remarquables & $f(-1) = 0$ & $f(3) = 0$ & \\\\ \\hline end{tabular}",
          "sympy": "x**2 - 2*x - 3",
          "correct": true,
          "error_type": ""
        },
        {
          "latex": "Le tableau de variations complet de $f$ est donné par : \\begin{tabular}{|c|c|c|c|c|}hline Intervalles & $(-\\infty,-1)$ & $(-1,3)$ & $(3,+\\infty)$ \\\\ \\hline Signe de $f'(x)$ & $-$ & $+$ & $-$ \\\\ \\hline Variations de $f$ & $\\searrow$ & $\\nearrow$ & $\\searrow$ \\\\ \\hline Limites aux bornes & $\\lim\\limits_{x\\to -\\infty} f(x) = -\\infty$ & & $\\lim\\limits_{x\\to +\\infty} f(x) = +\\infty$ \\\\ \\hline Valeurs remarquables & $f(-1) = 0$ & $f(3) = 0$ & \\\\ \\hline end{tabular}",
          "sympy": "-x**2 + 2*x + 3",
          "correct": false,
          "error_type": "inverse_sign"
        },
        {
          "latex": "Le tableau de variations complet de $f$ est donné par : \\begin{tabular}{|c|c|c|c|c|}hline Intervalles & $(-\\infty,-1)$ & $(-1,3)$ & $(3,+\\infty)$ \\\\ \\hline Signe de $f'(x)$ & $+$ & $-$ & $+$ \\\\ \\hline Variations de $f$ & $\\nearrow$ & $\\searrow$ & $\\nearrow$ \\\\ \\hline Limites aux bornes & $\\lim\\limits_{x\\to -\\infty} f(x) = -\\infty$ & & $\\lim\\limits_{x\\to +\\infty} f(x) = -\\infty$ \\\\ \\hline Valeurs remarquables & $f(-1) = 0$ & $f(3) = 0$ & \\\\ \\hline end{tabular}",
          "sympy": "x**2 + 2*x + 3",
          "correct": false,
          "error_type": "wrong_infinity"
        },
        {
          "latex": "Le tableau de variations complet de $f$ est donné par : \\begin{tabular}{|c|c|c|c|c|}hline Intervalles & $(-\\infty,-1)$ & $(-1,3)$ & $(3,+\\infty)$ \\\\ \\hline Signe de $f'(x)$ & $-$ & $+$ & $-$ \\\\ \\hline Variations de $f$ & $\\searrow$ & $\\nearrow$ & $\\searrow$ \\\\ \\hline Limites aux bornes & $\\lim\\limits_{x\\to -\\infty} f(x) = +\\infty$ & & $\\lim\\limits_{x\\to +\\infty} f(x) = +\\infty$ \\\\ \\hline Valeurs remarquables & $f(-1) = 0$ & $f(3) = 0$ & \\\\ \\hline end{tabular}",
          "sympy": "-x**2 - 2*x - 3",
          "correct": false,
          "error_type": "both_sign_and_infinity"
        }
      ],
      "check": {
        "kind": "manual"
      }
    }
  },
  {
    "skill_id": "ana1-etude-02",
    "difficulty": 3,
    "validation": "manual",
    "payload": {
      "skill_id": "ana1-etude-02",
      "format": "qcm",
      "difficulty": 3,
      "statement_latex": "Soit $f$ la fonction d'efinie par $f(x) = \\dfrac{x^3 - 2x^2 - 5x + 6}{x - 2}$. Quel est le tableau de variations complet de $f$ ?",
      "hints": [
        "Étudiez d'abord la dérivée de la fonction pour connaître les intervalles de variation.",
        "Construisez ensuite le tableau de variations en considérant les limites aux bornes et les valeurs remarquables."
      ],
      "solution_latex": "Le tableau de variations complet de $f$ est donné par : \\begin{tabular}{|c|c|c|c|c|}hline Intervalles & $(-\\infty,2)$ & $(2,+\\infty)$ \\\\ \\hline Signe de $f'(x)$ & $+$ & $+$ \\\\ \\hline Variations de $f$ & $\\nearrow$ & $\\nearrow$ \\\\ \\hline Limites aux bornes & $\\lim\\limits_{x\\to -\\infty} f(x) = -\\infty$ & $\\lim\\limits_{x\\to +\\infty} f(x) = +\\infty$ \\\\ \\hline Valeurs remarquables &  & $f(2) = 0$ \\\\ \\hline end{tabular}",
      "choices": [
        {
          "latex": "Le tableau de variations complet de $f$ est donné par : \\begin{tabular}{|c|c|c|c|c|}hline Intervalles & $(-\\infty,2)$ & $(2,+\\infty)$ \\\\ \\hline Signe de $f'(x)$ & $+$ & $+$ \\\\ \\hline Variations de $f$ & $\\nearrow$ & $\\nearrow$ \\\\ \\hline Limites aux bornes & $\\lim\\limits_{x\\to -\\infty} f(x) = -\\infty$ & $\\lim\\limits_{x\\to +\\infty} f(x) = +\\infty$ \\\\ \\hline Valeurs remarquables &  & $f(2) = 0$ \\\\ \\hline end{tabular}",
          "sympy": "(x**3 - 2*x**2 - 5*x + 6)/(x-2)",
          "correct": true,
          "error_type": ""
        },
        {
          "latex": "Le tableau de variations complet de $f$ est donné par : \\begin{tabular}{|c|c|c|c|c|}hline Intervalles & $(-\\infty,2)$ & $(2,+\\infty)$ \\\\ \\hline Signe de $f'(x)$ & $-$ & $-$ \\\\ \\hline Variations de $f$ & $\\searrow$ & $\\searrow$ \\\\ \\hline Limites aux bornes & $\\lim\\limits_{x\\to -\\infty} f(x) = +\\infty$ & $\\lim\\limits_{x\\to +\\infty} f(x) = -\\infty$ \\\\ \\hline Valeurs remarquables &  & $f(2) = 0$ \\\\ \\hline end{tabular}",
          "sympy": "(-(x**3 - 2*x**2 - 5*x + 6))/(x-2)",
          "correct": false,
          "error_type": "inverse_sign"
        },
        {
          "latex": "Le tableau de variations complet de $f$ est donné par : \\begin{tabular}{|c|c|c|c|c|}hline Intervalles & $(-\\infty,2)$ & $(2,+\\infty)$ \\\\ \\hline Signe de $f'(x)$ & $+$ & $+$ \\\\ \\hline Variations de $f$ & $\\nearrow$ & $\\nearrow$ \\\\ \\hline Limites aux bornes & $\\lim\\limits_{x\\to -\\infty} f(x) = +\\infty$ & $\\lim\\limits_{x\\to +\\infty} f(x) = +\\infty$ \\\\ \\hline Valeurs remarquables &  & $f(2) = 0$ \\\\ \\hline end{tabular}",
          "sympy": "((x**3 - 2*x**2 - 5*x + 6))/(x+2)",
          "correct": false,
          "error_type": "wrong_infinity"
        },
        {
          "latex": "Le tableau de variations complet de $f$ est donné par : \\begin{tabular}{|c|c|c|c|c|}hline Intervalles & $(-\\infty,2)$ & $(2,+\\infty)$ \\\\ \\hline Signe de $f'(x)$ & $-$ & $-$ \\\\ \\hline Variations de $f$ & $\\searrow$ & $\\searrow$ \\\\ \\hline Limites aux bornes & $\\lim\\limits_{x\\to -\\infty} f(x) = -\\infty$ & $\\lim\\limits_{x\\to +\\infty} f(x) = -\\infty$ \\\\ \\hline Valeurs remarquables &  & $f(2) = 0$ \\\\ \\hline end{tabular}",
          "sympy": "(-(x**3 - 2*x**2 - 5*x + 6))/(x+2)",
          "correct": false,
          "error_type": "both_sign_and_infinity"
        }
      ],
      "check": {
        "kind": "manual"
      }
    }
  },
  {
    "skill_id": "ana1-etude-02",
    "difficulty": 2,
    "validation": "manual",
    "payload": {
      "skill_id": "ana1-etude-02",
      "format": "qcm_theorique",
      "difficulty": 2,
      "statement_latex": "Soit $f$ la fonction d'efinie par $f(x) = x^2 - 5x + 6$. Quel est le tableau de variations complet de $f$ ?",
      "hints": [
        "Commencez par factoriser $f(x)$ pour trouver les racines et les points de rebroussement.",
        "Utilisez ensuite la dérivée de $f$ pour déterminer les intervalles de croissance et de décroissance."
      ],
      "solution_latex": "Le tableau de variations complet de $f$ est donné par : $f'(x) = 2x - 5$, $f'(x) = 0$ pour $x = \\dfrac{5}{2}$, $\\lim\\limits_{x\\to -\\infty} f(x) = +\\infty$, $\\lim\\limits_{x\\to +\\infty} f(x) = +\\infty$, $f(2) = 0$, $f(3) = 0$",
      "choices": [
        {
          "latex": "Le tableau de variations complet de $f$ est donné par : $f'(x) = 2x - 5$, $f'(x) = 0$ pour $x = \\dfrac{5}{2}$, $\\lim\\limits_{x\\to -\\infty} f(x) = +\\infty$, $\\lim\\limits_{x\\to +\\infty} f(x) = +\\infty$, $f(2) = 0$, $f(3) = 0$",
          "correct": true,
          "error_type": null
        },
        {
          "latex": "Le tableau de variations complet de $f$ est donné par : $f'(x) = x - 5$, $f'(x) = 0$ pour $x = 5$, $\\lim\\limits_{x\\to -\\infty} f(x) = -\\infty$, $\\lim\\limits_{x\\to +\\infty} f(x) = +\\infty$, $f(2) = 0$, $f(3) = 0$",
          "correct": false,
          "error_type": "hypothese_manquante"
        },
        {
          "latex": "Le tableau de variations complet de $f$ est donné par : $f'(x) = 2x - 5$, $f'(x) = 0$ pour $x = 2$, $\\lim\\limits_{x\\to -\\infty} f(x) = +\\infty$, $\\lim\\limits_{x\\to +\\infty} f(x) = +\\infty$, $f(2) = 0$, $f(3) = 0$",
          "correct": false,
          "error_type": "erreur_de_calcule"
        },
        {
          "latex": "Le tableau de variations complet de $f$ est donné par : $f'(x) = 2x - 5$, $f'(x) = 0$ pour $x = \\dfrac{5}{2}$, $\\lim\\limits_{x\\to -\\infty} f(x) = -\\infty$, $\\lim\\limits_{x\\to +\\infty} f(x) = +\\infty$, $f(2) = 0$, $f(3) = 0$",
          "correct": false,
          "error_type": "confusion_tvi_bornes"
        }
      ],
      "check": {
        "kind": "manual"
      }
    }
  },
  {
    "skill_id": "ana1-etude-02",
    "difficulty": 3,
    "validation": "manual",
    "payload": {
      "skill_id": "ana1-etude-02",
      "format": "qcm_theorique",
      "difficulty": 3,
      "statement_latex": "Soit $f$ la fonction d'efinie par $f(x) = \\dfrac{x^2 + 1}{x - 1}$. Quel est le tableau de variations complet de $f$ ?",
      "hints": [
        "Commencez par simplifier l'expression de $f(x)$ pour obtenir une forme plus simple.",
        "Utilisez ensuite la dérivée de $f$ pour déterminer les intervalles de croissance et de décroissance."
      ],
      "solution_latex": "Le tableau de variations complet de $f$ est donné par : $f'(x) = \\dfrac{x^2 + 2x + 1}{(x - 1)^2}$, $f'(x) > 0$ pour tout $x \\in \\mathbb{R} \\setminus \\{1\\}$, $\\lim\\limits_{x\\to 1^+} f(x) = +\\infty$, $\\lim\\limits_{x\\to 1^-} f(x) = -\\infty$, $\\lim\\limits_{x\\to +\\infty} f(x) = 1$",
      "choices": [
        {
          "latex": "Le tableau de variations complet de $f$ est donné par : $f'(x) = \\dfrac{x^2 + 2x + 1}{(x - 1)^2}$, $f'(x) > 0$ pour tout $x \\in \\mathbb{R} \\setminus \\{1\\}$, $\\lim\\limits_{x\\to 1^+} f(x) = +\\infty$, $\\lim\\limits_{x\\to 1^-} f(x) = -\\infty$, $\\lim\\limits_{x\\to +\\infty} f(x) = 1$",
          "correct": true,
          "error_type": null
        },
        {
          "latex": "Le tableau de variations complet de $f$ est donné par : $f'(x) = \\dfrac{x^2 + 2x - 1}{(x - 1)^2}$, $f'(x) > 0$ pour tout $x \\in \\mathbb{R} \\setminus \\{1\\}$, $\\lim\\limits_{x\\to 1^+} f(x) = +\\infty$, $\\lim\\limits_{x\\to 1^-} f(x) = -\\infty$, $\\lim\\limits_{x\\to +\\infty} f(x) = 1$",
          "correct": false,
          "error_type": "erreur_de_calcule"
        },
        {
          "latex": "Le tableau de variations complet de $f$ est donné par : $f'(x) = \\dfrac{x^2 + 2x + 1}{(x - 1)^2}$, $f'(x) = 0$ pour $x = 1$, $\\lim\\limits_{x\\to 1^+} f(x) = +\\infty$, $\\lim\\limits_{x\\to 1^-} f(x) = -\\infty$, $\\lim\\limits_{x\\to +\\infty} f(x) = 1$",
          "correct": false,
          "error_type": "hypothese_manquante"
        },
        {
          "latex": "Le tableau de variations complet de $f$ est donné par : $f'(x) = \\dfrac{x^2 + 2x + 1}{(x - 1)^2}$, $f'(x) < 0$ pour tout $x \\in \\mathbb{R} \\setminus \\{1\\}$, $\\lim\\limits_{x\\to 1^+} f(x) = +\\infty$, $\\lim\\limits_{x\\to 1^-} f(x) = -\\infty$, $\\lim\\limits_{x\\to +\\infty} f(x) = 1$",
          "correct": false,
          "error_type": "reciproque_fausse"
        }
      ],
      "check": {
        "kind": "manual"
      }
    }
  },
  {
    "skill_id": "ana1-etude-02",
    "difficulty": 2,
    "validation": "manual",
    "payload": {
      "skill_id": "ana1-etude-02",
      "format": "remise_en_ordre",
      "difficulty": 2,
      "statement_latex": "Reconstitue l'énoncé du théorème suivant : Théorème de Rolle - Soit $f$ une fonction définie sur $[a, b]$ et $f(a) = f(b) = 0$. Alors il existe un nombre réel $c$ tel que $a < c < b$ et $f'(c) = 0$.",
      "hints": [
        "Pensez à une fonction paire sur $[a, b]$ pour laquelle ce théorème s'applique.",
        "Rappellez-vous les hypothèses du théorème de Rolle : la fonction doit être continue sur l'intervalle fermé et dérivable sur l'intervalle ouvert"
      ],
      "solution_latex": "Soit $f$ une fonction définie sur $[a, b]$ telle que $f(a) = f(b) = 0$. Si $f$ est continue sur $[a, b]$ et dérivable sur $]a, b[$, alors il existe un nombre réel $c$ tel que $a < c < b$ et $f'(c) = 0$.",
      "fragments": [
        "Soit $f$ une fonction définie sur $[a, b]$ telle que $f(a) = f(b) = 0$.",
        "Si $f$ est continue sur $[a, b]$ et dérivable sur $]a, b[$",
        "alors il existe un nombre réel $c$ tel que $a < c < b$",
        "et $f'(c) = 0$."
      ],
      "distracteurs": [
        "et $f(c) = 0$",
        "alors il existe un nombre réel $c$ tel que $c < a$"
      ],
      "check": {
        "kind": "manual"
      }
    }
  },
  {
    "skill_id": "ana1-etude-02",
    "difficulty": 2,
    "validation": "manual",
    "payload": {
      "skill_id": "ana1-etude-02",
      "format": "remise_en_ordre",
      "difficulty": 2,
      "statement_latex": "Reconstitue l'énoncé de la définition d'une fonction paire.",
      "hints": [
        "Repensez à la symétrie par rapport à l'origine des fonctions paires.",
        "Rappellez-vous la définition d'une fonction paire : $f(-x) = f(x)$ pour tout $x$ dans le domaine de $f$"
      ],
      "solution_latex": "Une fonction $f$ définie sur un intervalle symétrique par rapport à l'origine est dite paire si $f(-x) = f(x)$ pour tout $x$ dans son domaine.",
      "fragments": [
        "Une fonction $f$ définie sur un intervalle symétrique par rapport à l'origine",
        "est dite paire si",
        "$f(-x) = f(x)$",
        "pour tout $x$ dans son domaine."
      ],
      "distracteurs": [
        "pour tout $x$ dans l'intervalle $[0, +infty[$"
      ],
      "check": {
        "kind": "manual"
      }
    }
  }
]